__iggy__/__init__.py
__iggy__/parsers.py
__iggy__/profile_parser.py
__iggy__/query.py
__iggy__/sif_parser.py
__iggy__/utils.py
__iggy__/encodings/add_edges.lp
__iggy__/encodings/add_influence.lp
__iggy__/encodings/backward_propagation.lp
__iggy__/encodings/best_one_edge.lp
__iggy__/encodings/best_one_edge_start.lp
__iggy__/encodings/contradictory_obs.lp
__iggy__/encodings/elementary_path_constraint.lp
__iggy__/encodings/error_measure.lp
__iggy__/encodings/flip_edges.lp
__iggy__/encodings/forward_propagation.lp
__iggy__/encodings/founded_constraints.lp
__iggy__/encodings/guess_inputs.lp
__iggy__/encodings/heuristic.lp
__iggy__/encodings/keep_inputs_constraint.lp
__iggy__/encodings/keep_observations_constraint.lp
__iggy__/encodings/mics.lp
__iggy__/encodings/mics_constrained_zero.lp
__iggy__/encodings/mics_founded_constraints.lp
__iggy__/encodings/mics_luca_constraints.lp
__iggy__/encodings/minimize_added_edges.lp
__iggy__/encodings/minimize_added_influences.lp
__iggy__/encodings/minimize_removed_edges.lp
__iggy__/encodings/minimize_repairs.lp
__iggy__/encodings/minimize_unweighted_error.lp
__iggy__/encodings/minimize_weighted_error.lp
__iggy__/encodings/minimize_weighted_repairs.lp
__iggy__/encodings/one_state.lp
__iggy__/encodings/path_constraint.lp
__iggy__/encodings/remove_edges.lp
__iggy__/encodings/show_errors.lp
__iggy__/encodings/show_predictions.lp
__iggy__/encodings/show_predictions_dm.lp
__iggy__/encodings/show_repairs.lp
__iggy__/encodings/show_vlabels.lp
__iggy__/encodings/sign-cons-3.lp
iggy-1.4.2.data/scripts/iggy.py
iggy-1.4.2.data/scripts/opt_graph.py
iggy-1.4.2.dist-info/METADATA
iggy-1.4.2.dist-info/RECORD
iggy-1.4.2.dist-info/WHEEL
iggy-1.4.2.dist-info/top_level.txt
