Metadata-Version: 2.1
Name: iggy
Version: 1.4.2
Summary: A tool for consistency based analysis of influence graphs and observed systems behavior.
Home-page: http://bioasp.github.io/iggy/
Author: Sven Thiele
Author-email: sthiele78@gmail.com
License: GPLv3+
Platform: UNKNOWN
Requires-Dist: pyasp (==1.4.3)
